FrameHarvest/__init__.py
FrameHarvest/dataset_generator.py
FrameHarvest-0.3.0.dist-info/METADATA
FrameHarvest-0.3.0.dist-info/WHEEL
FrameHarvest-0.3.0.dist-info/top_level.txt
FrameHarvest-0.3.0.dist-info/RECORD
