Metadata-Version: 2.1
Name: FrameHarvest
Version: 0.3.0
Requires-Dist: opencv-python
